migratik/__init__.py
migratik/config.py
migratik/console_scripts.py
migratik/errors.py
migratik/migrator.py
migratik/types.py
migratik/version_list.py
migratik/backends/__init__.py
migratik/backends/backend.py
migratik/backends/connection.py
migratik/backends/cursor.py
migratik/backends/psycopg2/__init__.py
migratik/backends/psycopg2/backend.py
migratik/backends/psycopg2/connection.py
migratik/backends/psycopg2/cursor.py
migratik-0.3.2.dist-info/METADATA
migratik-0.3.2.dist-info/WHEEL
migratik-0.3.2.dist-info/entry_points.txt
migratik-0.3.2.dist-info/licenses/LICENSE
migratik-0.3.2.dist-info/RECORD
