Metadata-Version: 2.1
Name: migratik
Version: 0.3.2
Summary: A database migration tool.
Project-URL: Homepage, https://github.com/Abstract-X/migratik
Project-URL: Bug Tracker, https://github.com/Abstract-X/migratik/issues
Author-email: Abstract-X <abstract-x-mail@protonmail.com>
License: MIT License
License-File: LICENSE
Classifier: License :: OSI Approved :: MIT License
Classifier: Operating System :: OS Independent
Classifier: Programming Language :: Python :: 3
Requires-Python: >=3.9
Requires-Dist: pyyaml<7,>=6.0.1
